{"acrobatics":0,"actions":[{"_Action_Type":-1,"attack_bonus":0,"damage_bonus":0,"desc":"The dragon makes three attacks: one with its bite and two with its claws.","_ID":-1,"_MonsterID":-1,"name":"Multiattack","_User_Created":false},{"_Action_Type":-1,"attack_bonus":10,"damage_bonus":6,"damage_dice":"2d10","desc":"Melee Weapon Attack: +10 to hit, reach 10 ft., one target. Hit: 17 (2d10 + 6) piercing damage.","_ID":-1,"_MonsterID":-1,"name":"Bite","_User_Created":false},{"_Action_Type":-1,"attack_bonus":10,"damage_bonus":6,"damage_dice":"2d6","desc":"Melee Weapon Attack: +10 to hit, reach 5 ft., one target. Hit: 13 (2d6 + 6) slashing damage.","_ID":-1,"_MonsterID":-1,"name":"Claw","_User_Created":false},{"_Action_Type":-1,"attack_bonus":0,"damage_bonus":0,"damage_dice":"10d10","desc":"The dragon uses one of the following breath weapons.\nFire Breath. The dragon exhales fire in a 30-foot cone. Each creature in that area must make a DC 17 Dexterity saving throw, taking 55 (10d10) fire damage on a failed save, or half as much damage on a successful one.\nWeakening Breath. The dragon exhales gas in a 30-foot cone. Each creature in that area must succeed on a DC 17 Strength saving throw or have disadvantage on Strength-based attack rolls, Strength checks, and Strength saving throws for 1 minute. A creature can repeat the saving throw at the end of each of its turns, ending the effect on itself on a success.","_ID":-1,"_MonsterID":-1,"name":"Breath Weapons (Recharge 5-6)","_User_Created":false}],"alignment":"lawful good","animal_handling":0,"arcana":0,"armor_class":18,"athletics":0,"challenge_rating":"10","charisma":20,"charisma_save":9,"condition_immunities":"","constitution":21,"constitution_save":9,"damage_immunities":"fire","damage_resistances":"","damage_vulnerabilities":"","deception":0,"dexterity":14,"dexterity_save":6,"history":0,"hit_dice":"17d10","hit_points":178,"_ID":-1,"insight":5,"intelligence":16,"intelligence_save":0,"intimidation":0,"investigation":0,"languages":"Common, Draconic","legendary_actions":[],"medicine":0,"name":"Young Gold Dragon","nature":0,"perception":9,"performance":0,"persuasion":9,"religion":0,"senses":"blindsight 30 ft., darkvision 120 ft., passive Perception 19","size":"Large","sleight_of_hand":0,"special_abilities":[{"_Action_Type":-1,"attack_bonus":0,"damage_bonus":0,"desc":"The dragon can breathe air and water.","_ID":-1,"_MonsterID":-1,"name":"Amphibious","_User_Created":false}],"speed":"40 ft., fly 80 ft., swim 40 ft.","stealth":6,"strength":23,"strength_save":0,"subtype":"","survival":0,"type":"dragon","_User_Created":false,"wisdom":13,"wisdom_save":5}